{
 "geoblacklight_version": "1.0",
 "dc_identifier_s": "c10d6961-e6e9-40fd-80c7-59be6f21bc7a",
 "dc_title_s": "LiDAR-Derived Classified LAS for Pepin County, WI 2019",
 "dc_description_s": "This data represents LiDAR-derived classified LAS points for Pepin County, Wisconsin in 2019. Point classification uses semi-automated techniques on the point cloud to assign the feature type associated with each point. LiDAR points can be classified into a number of categories including bare earth or ground, top of canopy, and water. The different classes are defined using numeric integer codes in the LAS files.",
 "dc_rights_s": "Public",
 "dct_provenance_s": "WisconsinView",
 "layer_id_s": "",
 "layer_slug_s": "c10d6961-e6e9-40fd-80c7-59be6f21bc7a",
 "layer_geom_type_s": "Point",
 "layer_modified_dt": "2022-01-22T20:12:43Z",
 "dc_format_s": "LAS",
 "dc_language_s": "English",
 "dct_isPartOf_sm": [
  "Wisconsin Elevation Data"
 ],
 "dc_creator_sm": [
  "U.S. Geological Survey"
 ],
 "dc_publisher_sm": "",
 "dc_type_s": "Dataset",
 "dc_subject_sm": [
  "Elevation"
 ],
 "dct_spatial_sm": [
  ""
 ],
 "dct_temporal_sm": [
  "2019"
 ],
 "solr_year_i": 2019,
 "dct_issued_s": "",
 "dct_references_s": "{\"http://schema.org/url\":\"https://www.sco.wisc.edu/data/elevationlidar/\",\"https://openindexmaps.org\":\"https://web.s3.wisc.edu/rml-gisdata/indexes/pepin3DEP-2019-ClassifiedPoints.geojson\",\"http://www.isotc211.org/schemas/2005/gmd/\":\"https://web.s3.wisc.edu/rml-gisdata/metadata/Pepin_LIDAR_USGS_2019.xml\"}",
 "solr_geom": "ENVELOPE(-92.318654,-91.648216,44.685939,44.403718)",
 "thumbnail_path_ss": "",
 "uw_supplemental_s": "For detailed metadata please visit: https://web.s3.wisc.edu/wsco-wisconsinview/lidar/Pepin/Pepin_2019_3DEP_Delivery/Metadata/Metadata.zip",
 "uw_notice_s": "",
 "uw_deprioritize_item_b": false
}