{
"geoblacklight_version": "1.0",
"dc_identifier_s": "1803861F-B635-494B-98B7-0432EAE42FF9",
"dc_title_s": "Addresses Monroe County, WI 2021",
"dc_description_s": "This data represents addresses for Monroe County, Wisconsin in 2021.",
"dc_rights_s": "Public",
"dct_provenance_s": "UW-Madison Robinson Map Library",
"layer_id_s": "",
"layer_slug_s": "1803861F-B635-494B-98B7-0432EAE42FF9",
"layer_geom_type_s": "Point",
"dc_format_s": "Geodatabase",
"dc_language_s": "English",
"dct_isPartOf_sm": [],
"dc_creator_sm": ["Monroe County"],
"dc_publisher_sm": "",
"dc_type_s": "Dataset",
"dc_subject_sm": ["Location"],
"dct_spatial_sm": [],
"dct_issued_s": "",
"dct_temporal_sm": ["2021"],
"solr_year_i": 2021,
"dct_references_s": "{\"http://schema.org/downloadUrl\":\"https://gisdata.wisc.edu/public/MONROE_ADDRESSES_2021.zip\",\"http://www.isotc211.org/schemas/2005/gmd/\":\"https://gisdata.wisc.edu/public/metadata/MONROE_ADDRESSES_2021.xml\"}",
"solr_geom": "ENVELOPE(-90.983548, -90.310382, 44.161104, 43.722454)",
"uw_supplemental_s": "This is an archived copy of the data held at UW-Madison.",
"uw_notice_s": ""
}
