{
"geoblacklight_version": "1.0",
"dc_identifier_s": "6567DEB6-F1CA-4530-A5FE-6A9F78F120C3",
"dc_title_s": "EMS Response Districts Portage County, WI 2019",
"dc_description_s": "This data layer represents Emergency Medical Services (EMS) response districts in Portage County, Wisconsin in 2019.",
"dc_rights_s": "Public",
"dct_provenance_s": "UW-Madison Robinson Map Library",
"layer_id_s": "",
"layer_slug_s": "6567DEB6-F1CA-4530-A5FE-6A9F78F120C3",
"layer_geom_type_s": "Polygon",
"dc_format_s": "Shapefile",
"dc_language_s": "English",
"dct_isPartOf_sm": [],
"dc_creator_sm": ["Portage County"],
"dc_publisher_sm": "",
"dc_type_s": "Dataset",
"dc_subject_sm": ["Boundaries"],
"dct_spatial_sm": [],
"dct_issued_s": "",
"dct_temporal_sm": ["2019"],
"solr_year_i": 2019,
"dct_references_s": "{\"http://schema.org/downloadUrl\":\"https://gisdata.wisc.edu/public/Portage_EMS_2019.zip\",\"http://www.isotc211.org/schemas/2005/gmd/\":\"https://gisdata.wisc.edu/public/metadata/Portage_EMS_2019.xml\"}",
"solr_geom": "ENVELOPE(-89.845799, -89.222276, 44.685866, 44.243212)",
"uw_supplemental_s": "",
"uw_notice_s": ""
}
