{
"geoblacklight_version": "1.0",
"dc_identifier_s": "B23AF368-E24B-478B-B920-1636BD73F931",
"dc_title_s": "Roads Florence County, WI 2024",
"dc_description_s": "This data represents roads for Florence County, Wisconsin in 2024.",
"dc_rights_s": "Public",
"dct_provenance_s": "UW-Madison Robinson Map Library",
"layer_id_s": "",
"layer_slug_s": "B23AF368-E24B-478B-B920-1636BD73F931",
"layer_geom_type_s": "Line",
"layer_modified_dt": "2024-04-08T16:25:03Z",
"dc_format_s": "Geodatabase",
"dc_language_s": "English",
"dct_isPartOf_sm": [],
"dc_creator_sm": ["Florence County"],
"dc_publisher_sm": "",
"dc_type_s": "Dataset",
"dc_subject_sm": ["Transportation"],
"dct_spatial_sm": [],
"dct_issued_s": "",
"dct_temporal_sm": ["2024"],
"solr_year_i": 2024,
"dct_references_s": "{\"http://schema.org/downloadUrl\":\"https://gisdata.wisc.edu/public/FLORENCE_ROADS_2024.zip\",\"http://www.isotc211.org/schemas/2005/gmd/\":\"https://gisdata.wisc.edu/public/metadata/FLORENCE_ROADS_2024.xml\"}",
"solr_geom": "ENVELOPE(-88.684523, -88.04912, 46.020967, 45.645121)",
"uw_supplemental_s": "This is an archived copy of the data held at UW-Madison.",
"uw_notice_s": ""
}