{
"geoblacklight_version": "1.0",
"dc_identifier_s": "CE56AD20-78AD-4E76-8D02-D8A45940ED0B",
"dc_title_s": "Zoning City of Madison, WI 2023",
"dc_description_s": "This polygon data layer represents zoning for the City of Madison, Wisconsin in 2023. [City of Madison Zoning Districts - current This data layer is used by the Zoning Districts and Development Information applications.]",
"dc_rights_s": "Public",
"dct_provenance_s": "UW-Madison Robinson Map Library",
"layer_id_s": "",
"layer_slug_s": "CE56AD20-78AD-4E76-8D02-D8A45940ED0B",
"layer_geom_type_s": "Polygon",
"layer_modified_dt": "2023-08-15T18:27:26Z",
"dc_format_s": "Shapefile",
"dc_language_s": "English",
"dct_isPartOf_sm": [],
"dc_creator_sm": ["City of Madison"],
"dc_publisher_sm": "",
"dc_type_s": "Dataset",
"dc_subject_sm": ["Planning and Cadastral"],
"dct_spatial_sm": [],
"dct_issued_s": "",
"dct_temporal_sm": ["2023"],
"solr_year_i": 2023,
"dct_references_s": "{\"http://schema.org/downloadUrl\":\"https://gisdata.wisc.edu/public/Madison_City_Zoning_2023.zip\",\"http://schema.org/url\":\"http://data.cityofmadison.opendata.arcgis.com/\",\"http://www.isotc211.org/schemas/2005/gmd/\":\"https://gisdata.wisc.edu/public/metadata/Madison_City_Zoning_2023.xml\"}",
"solr_geom": "ENVELOPE(-89.57153, -89.242696, 43.17202, 42.998147)",
"uw_supplemental_s": "For additional information, please see: http://www.cityofmadison.com/dpced/",
"uw_notice_s": ""
}