{
"geoblacklight_version": "1.0",
"dc_identifier_s": "40F7D4D2-1234-4892-A7BC-C0A4EA6E5BBC",
"dc_title_s": "Addresses Polk County, WI 2024",
"dc_description_s": "This data represents addresses for Polk County, Wisconsin in 2024.",
"dc_rights_s": "Public",
"dct_provenance_s": "UW-Madison Robinson Map Library",
"layer_id_s": "",
"layer_slug_s": "40F7D4D2-1234-4892-A7BC-C0A4EA6E5BBC",
"layer_geom_type_s": "Point",
"layer_modified_dt": "2024-03-11T19:06:04Z",
"dc_format_s": "Geodatabase",
"dc_language_s": "English",
"dct_isPartOf_sm": [],
"dc_creator_sm": ["Polk County"],
"dc_publisher_sm": "",
"dc_type_s": "Dataset",
"dc_subject_sm": ["Location"],
"dct_spatial_sm": [],
"dct_issued_s": "",
"dct_temporal_sm": ["2024"],
"solr_year_i": 2024,
"dct_references_s": "{\"http://schema.org/downloadUrl\":\"https://gisdata.wisc.edu/public/POLK_ADDRESSES_2024.zip\",\"http://schema.org/url\":\"https://www.polkcountywi.gov/government/divisions_and_departments/environmental_services_division/land_information/gis_data_portal.php\",\"http://www.isotc211.org/schemas/2005/gmd/\":\"https://gisdata.wisc.edu/public/metadata/POLK_ADDRESSES_2024.xml\"}",
"solr_geom": "ENVELOPE(-92.88075, -92.085073, 45.728609, 45.135551)",
"uw_supplemental_s": "This is an archived copy of the data held at UW-Madison. For access to the most current data available, please visit: https://www.polkcountywi.gov/government/divisions_and_departments/environmental_services_division/land_information/gis_data_portal.php",
"uw_notice_s": ""
}