{
"geoblacklight_version": "1.0",
"dc_identifier_s": "91B3C42A-EB55-420D-8AF8-C2EAF58A6837",
"dc_title_s": "PLSS Shawano County, WI 2025",
"dc_description_s": "This data represents public land survey system (PLSS) corners for Shawano County, Wisconsin in 2025.",
"dc_rights_s": "Public",
"dct_provenance_s": "UW-Madison Robinson Map Library",
"layer_id_s": "",
"layer_slug_s": "91B3C42A-EB55-420D-8AF8-C2EAF58A6837",
"layer_geom_type_s": "Point",
"layer_modified_dt": "2025-04-21T20:05:00Z",
"dc_format_s": "Geodatabase",
"dc_language_s": "English",
"dct_isPartOf_sm": [],
"dc_creator_sm": ["Shawano County"],
"dc_publisher_sm": "",
"dc_type_s": "Dataset",
"dc_subject_sm": ["Planning and Cadastral"],
"dct_spatial_sm": [],
"dct_issued_s": "",
"dct_temporal_sm": ["2025"],
"solr_year_i": 2025,
"dct_references_s": "{\"http://schema.org/downloadUrl\":\"https://web.s3.wisc.edu/rml-gisdata/SHAWANO_PLSS_2025.zip\",\"http://www.isotc211.org/schemas/2005/gmd/\":\"https://web.s3.wisc.edu/rml-gisdata/metadata/SHAWANO_PLSS_2025.xml\"}",
"solr_geom": "ENVELOPE(-89.227583, -88.240483, 45.031069, 44.583645)",
"uw_supplemental_s": "This is an archived copy of the data held at UW-Madison.",
"uw_notice_s": ""
}