{
"geoblacklight_version": "1.0",
"dc_identifier_s": "09A81946-F756-47EC-B265-7601128854C3",
"dc_title_s": "Land Use Washington County, WI 1963",
"dc_description_s": "This data layer represents land use for Washington County, Wisconsin in 1963.",
"dc_rights_s": "Public",
"dct_provenance_s": "UW-Madison Robinson Map Library",
"layer_id_s": "",
"layer_slug_s": "09A81946-F756-47EC-B265-7601128854C3",
"layer_geom_type_s": "Polygon",
"layer_modified_dt": "2022-01-22T20:12:43Z",
"dc_format_s": "Shapefile",
"dc_language_s": "English",
"dct_isPartOf_sm": [],
"dc_creator_sm": ["Southeastern Wisconsin Regional Planning Commission"],
"dc_publisher_sm": "",
"dc_type_s": "Dataset",
"dc_subject_sm": ["Planning and Cadastral"],
"dct_spatial_sm": [],
"dct_issued_s": "",
"dct_temporal_sm": ["1963"],
"solr_year_i": 1963,
"dct_references_s": "{\"http://schema.org/downloadUrl\":\"https://gisdata.wisc.edu/public/Washington_LandUse_1963.zip\",\"http://www.isotc211.org/schemas/2005/gmd/\":\"https://gisdata.wisc.edu/public/metadata/Washington_LandUse_1963.xml\"}",
"solr_geom": "ENVELOPE(-88.422855, -88.03412, 43.548303, 43.188276)",
"uw_supplemental_s": "For more information: http://www.sewrpc.org/SEWRPC/LandUse.htm",
"uw_notice_s": ""
}