{
"geoblacklight_version": "1.0",
"dc_identifier_s": "D0812DE3-DD93-4444-8B43-DBDC496B2EB9",
"dc_title_s": "Major Land Resource Areas (MLRA), WI 2006",
"dc_description_s": "[Major land resource areas (MLRAs) are geographically associated land resource units (LRUs). Identification of these large areas is important in statewide agricultural planning and has value in interstate, regional, and national planning.]",
"dc_rights_s": "Public",
"dct_provenance_s": "UW-Madison Robinson Map Library",
"layer_id_s": "",
"layer_slug_s": "D0812DE3-DD93-4444-8B43-DBDC496B2EB9",
"layer_geom_type_s": "Polygon",
"layer_modified_dt": "2022-01-22T20:12:43Z",
"dc_format_s": "Geodatabase",
"dc_language_s": "English",
"dct_isPartOf_sm": ["Statewide"],
"dc_creator_sm": ["U.S. Department of Agriculture – Natural Resources Conservation Service"],
"dc_publisher_sm": "",
"dc_type_s": "Dataset",
"dc_subject_sm": ["Farming"],
"dct_spatial_sm": [],
"dct_issued_s": "",
"dct_temporal_sm": ["2006"],
"solr_year_i": 2006,
"dct_references_s": "{\"http://schema.org/downloadUrl\":\"https://gisdata.wisc.edu/public/WI_Soils_MLRA_2006.zip\",\"http://schema.org/url\":\"https://datagateway.nrcs.usda.gov/ \",\"http://www.isotc211.org/schemas/2005/gmd/\":\"https://gisdata.wisc.edu/public/metadata/WI_Soils_MLRA_2006.xml\"}",
"solr_geom": "ENVELOPE(-94.352264, -83.897937, 47.479532, 40.157311)",
"uw_supplemental_s": "This is an archived copy of the data held at UW-Madison.  For the most recent verison of this data please visit: https://datagateway.nrcs.usda.gov/",
"uw_notice_s": ""
}